healthcheck.py
hfl_healthcheck-0.0.3.dist-info/METADATA
hfl_healthcheck-0.0.3.dist-info/WHEEL
hfl_healthcheck-0.0.3.dist-info/top_level.txt
hfl_healthcheck-0.0.3.dist-info/RECORD
