Metadata-Version: 2.2
Name: hfl-healthcheck
Version: 0.0.3
Summary: Send healthchecks to dedicated endpoint
Requires-Python: >=3.7
Requires-Dist: requests
